odoo/addons/l10n_pt_payment/README.rst
odoo/addons/l10n_pt_payment/__init__.py
odoo/addons/l10n_pt_payment/__manifest__.py
odoo/addons/l10n_pt_payment/data/payment_method_data.xml
odoo/addons/l10n_pt_payment/i18n/l10n_pt_payment.pot
odoo/addons/l10n_pt_payment/readme/CONTRIBUTORS.md
odoo/addons/l10n_pt_payment/readme/DESCRIPTION.md
odoo/addons/l10n_pt_payment/readme/USAGE.md
odoo/addons/l10n_pt_payment/static/description/icon.png
odoo/addons/l10n_pt_payment/static/description/index.html
odoo/addons/l10n_pt_payment/static/img/mbway_icon.png
odoo/addons/l10n_pt_payment/static/img/multibanco_icon.png
odoo_addon_l10n_pt_payment-18.0.1.0.0.2.dist-info/METADATA
odoo_addon_l10n_pt_payment-18.0.1.0.0.2.dist-info/WHEEL
odoo_addon_l10n_pt_payment-18.0.1.0.0.2.dist-info/top_level.txt
odoo_addon_l10n_pt_payment-18.0.1.0.0.2.dist-info/RECORD
